curelyai/__init__.py
curelyai/chat.py
tests/__init__.py
tests/test_chat.py
curelyai-0.1.0.dist-info/LICENSE
curelyai-0.1.0.dist-info/METADATA
curelyai-0.1.0.dist-info/WHEEL
curelyai-0.1.0.dist-info/top_level.txt
curelyai-0.1.0.dist-info/RECORD
