Metadata-Version: 2.1
Name: curelyai
Version: 0.1.0
Summary: A Python client for Curely AI API
Home-page: https://github.com/curelyai/curelyai_python_package
Author: Curely Ai
Author-email: curelyai@gmail.com
Classifier: Programming Language :: Python :: 3
Classifier: License :: OSI Approved :: MIT License
Classifier: Operating System :: OS Independent
Requires-Python: >=3.6
License-File: LICENSE
Requires-Dist: requests
